requests_proxyport/__init__.py
requests_proxyport/__version__.py
requests_proxyport/requests_proxyport.py
requests_proxyport-0.0.2.dist-info/LICENSE
requests_proxyport-0.0.2.dist-info/METADATA
requests_proxyport-0.0.2.dist-info/WHEEL
requests_proxyport-0.0.2.dist-info/top_level.txt
requests_proxyport-0.0.2.dist-info/RECORD
