Metadata-Version: 2.1
Name: requests-proxyport
Version: 0.0.2
Summary: Proxy Port requests
Home-page: https://proxy-port.com/en/scraping-proxy
Author: Proxy Port
Author-email: Proxy Port <proxyportcom@gmail.com>
License: MIT License
Project-URL: Homepage, https://proxy-port.com/en/scraping-proxy
Project-URL: Bug Tracker, https://github.com/proxyport/py-requests-proxyport/issues
Classifier: License :: OSI Approved :: MIT License
Classifier: Development Status :: 3 - Alpha
Classifier: Operating System :: OS Independent
Classifier: Topic :: Internet :: Proxy Servers
Classifier: Topic :: Internet :: WWW/HTTP :: Session
Classifier: Intended Audience :: Developers
Classifier: Intended Audience :: Information Technology
Classifier: Intended Audience :: Science/Research
Classifier: Programming Language :: Python
Classifier: Programming Language :: Python :: 3
Classifier: Programming Language :: Python :: 3.6
Classifier: Programming Language :: Python :: 3.7
Classifier: Programming Language :: Python :: 3.8
Classifier: Programming Language :: Python :: 3.9
Classifier: Programming Language :: Python :: 3.10
Classifier: Programming Language :: Python :: 3.11
Classifier: Programming Language :: Python :: Implementation :: CPython
Classifier: Programming Language :: Python :: Implementation :: PyPy
Requires-Python: >=3.6.0
License-File: LICENSE
Requires-Dist: proxyport2
Requires-Dist: requests
